{"id": "46004-43281-013-LN2991", "info": "The project has three main components: (i) a medium-sized hydropower plant of 140 megawatts (MW) with significant water storage facilities and associated transmission lines to evacuate the generated power; (ii) rural electrification and community development in the project area, and (iii) a reform and restructuring plan for the national utility, the Nepal Electricity Authority (NEA). The project site is in the Seti River in the Tanahu district, about 150 kilometers (km) west of Kathmandu.", "bounds": [[80.03028772000005, 26.343767802000087, 88.1690674240001, 30.416904195000086]], "name": "TANAHU HYDROPOWER PROJECT(SF)", "locations": {"type": "Feature", "geometry": {"type": "MultiPoint", "coordinates": [[27.91667, 84.25], [28.33333, 82.5], [28.0, 84.0], [27.36667, 84.91667], [27.75, 83.5], [27.68333, 84.43333], [29.05977, 82.31335], [27.45436, 85.22301], [28.17039, 83.93829], [28.02937, 83.21184], [28.07217, 82.90132], [27.97763, 84.26486]]}}}