{
  "features": [
    {
      "geometry": {
        "coordinates": [
          101.5, 
          18.5
        ], 
        "type": "Point"
      }, 
      "id": "7781", 
      "properties": {
        "approvalDate": "2009-11-23", 
        "closingDate": "2012-08-31", 
        "commitmentAmount": 10000000.0, 
        "disbursementAmount": 10000000.0, 
        "id": "41376-022", 
        "info": "The Health Sector Development Program (the HSDP), consisting of a program grant for policy reforms and an accompanying project grant, will support the Government's 7th Health Sector Development Plan,\u2026", 
        "locationName": "Xaignabouli", 
        "sectors": [
          "Health"
        ], 
        "status": "Completion", 
        "title": "HEALTH SECTOR DEVELOPMENT PROGRAM"
      }, 
      "type": "Feature"
    }, 
    {
      "geometry": {
        "coordinates": [
          102.41667, 
          18.75
        ], 
        "type": "Point"
      }, 
      "id": "7782", 
      "properties": {
        "approvalDate": "2009-11-23", 
        "closingDate": "2012-08-31", 
        "commitmentAmount": 10000000.0, 
        "disbursementAmount": 10000000.0, 
        "id": "41376-022", 
        "info": "The Health Sector Development Program (the HSDP), consisting of a program grant for policy reforms and an accompanying project grant, will support the Government's 7th Health Sector Development Plan,\u2026", 
        "locationName": "Vientiane Province", 
        "sectors": [
          "Health"
        ], 
        "status": "Completion", 
        "title": "HEALTH SECTOR DEVELOPMENT PROGRAM"
      }, 
      "type": "Feature"
    }, 
    {
      "geometry": {
        "coordinates": [
          105.75, 
          16.5
        ], 
        "type": "Point"
      }, 
      "id": "7783", 
      "properties": {
        "approvalDate": "2009-11-23", 
        "closingDate": "2012-08-31", 
        "commitmentAmount": 10000000.0, 
        "disbursementAmount": 10000000.0, 
        "id": "41376-022", 
        "info": "The Health Sector Development Program (the HSDP), consisting of a program grant for policy reforms and an accompanying project grant, will support the Government's 7th Health Sector Development Plan,\u2026", 
        "locationName": "Khoueng Savannakhet", 
        "sectors": [
          "Health"
        ], 
        "status": "Completion", 
        "title": "HEALTH SECTOR DEVELOPMENT PROGRAM"
      }, 
      "type": "Feature"
    }, 
    {
      "geometry": {
        "coordinates": [
          106.25, 
          15.75
        ], 
        "type": "Point"
      }, 
      "id": "7784", 
      "properties": {
        "approvalDate": "2009-11-23", 
        "closingDate": "2012-08-31", 
        "commitmentAmount": 10000000.0, 
        "disbursementAmount": 10000000.0, 
        "id": "41376-022", 
        "info": "The Health Sector Development Program (the HSDP), consisting of a program grant for policy reforms and an accompanying project grant, will support the Government's 7th Health Sector Development Plan,\u2026", 
        "locationName": "Salavan", 
        "sectors": [
          "Health"
        ], 
        "status": "Completion", 
        "title": "HEALTH SECTOR DEVELOPMENT PROGRAM"
      }, 
      "type": "Feature"
    }, 
    {
      "geometry": {
        "coordinates": [
          102.33333, 
          21.75
        ], 
        "type": "Point"
      }, 
      "id": "7785", 
      "properties": {
        "approvalDate": "2009-11-23", 
        "closingDate": "2012-08-31", 
        "commitmentAmount": 10000000.0, 
        "disbursementAmount": 10000000.0, 
        "id": "41376-022", 
        "info": "The Health Sector Development Program (the HSDP), consisting of a program grant for policy reforms and an accompanying project grant, will support the Government's 7th Health Sector Development Plan,\u2026", 
        "locationName": "Khoueng Phongsali", 
        "sectors": [
          "Health"
        ], 
        "status": "Completion", 
        "title": "HEALTH SECTOR DEVELOPMENT PROGRAM"
      }, 
      "type": "Feature"
    }, 
    {
      "geometry": {
        "coordinates": [
          101.5, 
          20.16667
        ], 
        "type": "Point"
      }, 
      "id": "7786", 
      "properties": {
        "approvalDate": "2009-11-23", 
        "closingDate": "2012-08-31", 
        "commitmentAmount": 10000000.0, 
        "disbursementAmount": 10000000.0, 
        "id": "41376-022", 
        "info": "The Health Sector Development Program (the HSDP), consisting of a program grant for policy reforms and an accompanying project grant, will support the Government's 7th Health Sector Development Plan,\u2026", 
        "locationName": "Khoueng Oudomxai", 
        "sectors": [
          "Health"
        ], 
        "status": "Completion", 
        "title": "HEALTH SECTOR DEVELOPMENT PROGRAM"
      }, 
      "type": "Feature"
    }, 
    {
      "geometry": {
        "coordinates": [
          102.66667, 
          20.25
        ], 
        "type": "Point"
      }, 
      "id": "7787", 
      "properties": {
        "approvalDate": "2009-11-23", 
        "closingDate": "2012-08-31", 
        "commitmentAmount": 10000000.0, 
        "disbursementAmount": 10000000.0, 
        "id": "41376-022", 
        "info": "The Health Sector Development Program (the HSDP), consisting of a program grant for policy reforms and an accompanying project grant, will support the Government's 7th Health Sector Development Plan,\u2026", 
        "locationName": "Luang Prabang Province", 
        "sectors": [
          "Health"
        ], 
        "status": "Completion", 
        "title": "HEALTH SECTOR DEVELOPMENT PROGRAM"
      }, 
      "type": "Feature"
    }, 
    {
      "geometry": {
        "coordinates": [
          101.33333, 
          20.91667
        ], 
        "type": "Point"
      }, 
      "id": "7788", 
      "properties": {
        "approvalDate": "2009-11-23", 
        "closingDate": "2012-08-31", 
        "commitmentAmount": 10000000.0, 
        "disbursementAmount": 10000000.0, 
        "id": "41376-022", 
        "info": "The Health Sector Development Program (the HSDP), consisting of a program grant for policy reforms and an accompanying project grant, will support the Government's 7th Health Sector Development Plan,\u2026", 
        "locationName": "Louangnamtha", 
        "sectors": [
          "Health"
        ], 
        "status": "Completion", 
        "title": "HEALTH SECTOR DEVELOPMENT PROGRAM"
      }, 
      "type": "Feature"
    }, 
    {
      "geometry": {
        "coordinates": [
          105.33333, 
          17.5
        ], 
        "type": "Point"
      }, 
      "id": "7789", 
      "properties": {
        "approvalDate": "2009-11-23", 
        "closingDate": "2012-08-31", 
        "commitmentAmount": 10000000.0, 
        "disbursementAmount": 10000000.0, 
        "id": "41376-022", 
        "info": "The Health Sector Development Program (the HSDP), consisting of a program grant for policy reforms and an accompanying project grant, will support the Government's 7th Health Sector Development Plan,\u2026", 
        "locationName": "Khammouan", 
        "sectors": [
          "Health"
        ], 
        "status": "Completion", 
        "title": "HEALTH SECTOR DEVELOPMENT PROGRAM"
      }, 
      "type": "Feature"
    }, 
    {
      "geometry": {
        "coordinates": [
          104.0, 
          20.5
        ], 
        "type": "Point"
      }, 
      "id": "7790", 
      "properties": {
        "approvalDate": "2009-11-23", 
        "closingDate": "2012-08-31", 
        "commitmentAmount": 10000000.0, 
        "disbursementAmount": 10000000.0, 
        "id": "41376-022", 
        "info": "The Health Sector Development Program (the HSDP), consisting of a program grant for policy reforms and an accompanying project grant, will support the Government's 7th Health Sector Development Plan,\u2026", 
        "locationName": "Houaphan", 
        "sectors": [
          "Health"
        ], 
        "status": "Completion", 
        "title": "HEALTH SECTOR DEVELOPMENT PROGRAM"
      }, 
      "type": "Feature"
    }, 
    {
      "geometry": {
        "coordinates": [
          106.0, 
          14.75
        ], 
        "type": "Point"
      }, 
      "id": "7791", 
      "properties": {
        "approvalDate": "2009-11-23", 
        "closingDate": "2012-08-31", 
        "commitmentAmount": 10000000.0, 
        "disbursementAmount": 10000000.0, 
        "id": "41376-022", 
        "info": "The Health Sector Development Program (the HSDP), consisting of a program grant for policy reforms and an accompanying project grant, will support the Government's 7th Health Sector Development Plan,\u2026", 
        "locationName": "Champasak", 
        "sectors": [
          "Health"
        ], 
        "status": "Completion", 
        "title": "HEALTH SECTOR DEVELOPMENT PROGRAM"
      }, 
      "type": "Feature"
    }, 
    {
      "geometry": {
        "coordinates": [
          102.6, 
          17.96667
        ], 
        "type": "Point"
      }, 
      "id": "7792", 
      "properties": {
        "approvalDate": "2009-11-23", 
        "closingDate": "2012-08-31", 
        "commitmentAmount": 10000000.0, 
        "disbursementAmount": 10000000.0, 
        "id": "41376-022", 
        "info": "The Health Sector Development Program (the HSDP), consisting of a program grant for policy reforms and an accompanying project grant, will support the Government's 7th Health Sector Development Plan,\u2026", 
        "locationName": "Vientiane", 
        "sectors": [
          "Health"
        ], 
        "status": "Completion", 
        "title": "HEALTH SECTOR DEVELOPMENT PROGRAM"
      }, 
      "type": "Feature"
    }, 
    {
      "geometry": {
        "coordinates": [
          103.5, 
          19.41667
        ], 
        "type": "Point"
      }, 
      "id": "7793", 
      "properties": {
        "approvalDate": "2009-11-23", 
        "closingDate": "2012-08-31", 
        "commitmentAmount": 10000000.0, 
        "disbursementAmount": 10000000.0, 
        "id": "41376-022", 
        "info": "The Health Sector Development Program (the HSDP), consisting of a program grant for policy reforms and an accompanying project grant, will support the Government's 7th Health Sector Development Plan,\u2026", 
        "locationName": "Xiangkhouang", 
        "sectors": [
          "Health"
        ], 
        "status": "Completion", 
        "title": "HEALTH SECTOR DEVELOPMENT PROGRAM"
      }, 
      "type": "Feature"
    }, 
    {
      "geometry": {
        "coordinates": [
          107.0, 
          14.66667
        ], 
        "type": "Point"
      }, 
      "id": "7794", 
      "properties": {
        "approvalDate": "2009-11-23", 
        "closingDate": "2012-08-31", 
        "commitmentAmount": 10000000.0, 
        "disbursementAmount": 10000000.0, 
        "id": "41376-022", 
        "info": "The Health Sector Development Program (the HSDP), consisting of a program grant for policy reforms and an accompanying project grant, will support the Government's 7th Health Sector Development Plan,\u2026", 
        "locationName": "Attapu", 
        "sectors": [
          "Health"
        ], 
        "status": "Completion", 
        "title": "HEALTH SECTOR DEVELOPMENT PROGRAM"
      }, 
      "type": "Feature"
    }, 
    {
      "geometry": {
        "coordinates": [
          107.0, 
          15.5
        ], 
        "type": "Point"
      }, 
      "id": "7795", 
      "properties": {
        "approvalDate": "2009-11-23", 
        "closingDate": "2012-08-31", 
        "commitmentAmount": 10000000.0, 
        "disbursementAmount": 10000000.0, 
        "id": "41376-022", 
        "info": "The Health Sector Development Program (the HSDP), consisting of a program grant for policy reforms and an accompanying project grant, will support the Government's 7th Health Sector Development Plan,\u2026", 
        "locationName": "Khoueng Xekong", 
        "sectors": [
          "Health"
        ], 
        "status": "Completion", 
        "title": "HEALTH SECTOR DEVELOPMENT PROGRAM"
      }, 
      "type": "Feature"
    }, 
    {
      "geometry": {
        "coordinates": [
          100.5, 
          20.5
        ], 
        "type": "Point"
      }, 
      "id": "7796", 
      "properties": {
        "approvalDate": "2009-11-23", 
        "closingDate": "2012-08-31", 
        "commitmentAmount": 10000000.0, 
        "disbursementAmount": 10000000.0, 
        "id": "41376-022", 
        "info": "The Health Sector Development Program (the HSDP), consisting of a program grant for policy reforms and an accompanying project grant, will support the Government's 7th Health Sector Development Plan,\u2026", 
        "locationName": "Khoueng Bokeo", 
        "sectors": [
          "Health"
        ], 
        "status": "Completion", 
        "title": "HEALTH SECTOR DEVELOPMENT PROGRAM"
      }, 
      "type": "Feature"
    }, 
    {
      "geometry": {
        "coordinates": [
          104.33333, 
          18.5
        ], 
        "type": "Point"
      }, 
      "id": "7797", 
      "properties": {
        "approvalDate": "2009-11-23", 
        "closingDate": "2012-08-31", 
        "commitmentAmount": 10000000.0, 
        "disbursementAmount": 10000000.0, 
        "id": "41376-022", 
        "info": "The Health Sector Development Program (the HSDP), consisting of a program grant for policy reforms and an accompanying project grant, will support the Government's 7th Health Sector Development Plan,\u2026", 
        "locationName": "Bolikhamxai", 
        "sectors": [
          "Health"
        ], 
        "status": "Completion", 
        "title": "HEALTH SECTOR DEVELOPMENT PROGRAM"
      }, 
      "type": "Feature"
    }, 
    {
      "geometry": {
        "coordinates": [
          102.66667, 
          18.08333
        ], 
        "type": "Point"
      }, 
      "id": "7798", 
      "properties": {
        "approvalDate": "2009-11-23", 
        "closingDate": "2012-08-31", 
        "commitmentAmount": 10000000.0, 
        "disbursementAmount": 10000000.0, 
        "id": "41376-022", 
        "info": "The Health Sector Development Program (the HSDP), consisting of a program grant for policy reforms and an accompanying project grant, will support the Government's 7th Health Sector Development Plan,\u2026", 
        "locationName": "Vientiane Prefecture", 
        "sectors": [
          "Health"
        ], 
        "status": "Completion", 
        "title": "HEALTH SECTOR DEVELOPMENT PROGRAM"
      }, 
      "type": "Feature"
    }, 
    {
      "geometry": {
        "coordinates": [
          101.5, 
          18.5
        ], 
        "type": "Point"
      }, 
      "id": "7799", 
      "properties": {
        "approvalDate": "2009-11-23", 
        "closingDate": "2015-06-30", 
        "commitmentAmount": 10000000.0, 
        "disbursementAmount": 9999999.999999998, 
        "id": "41376-022", 
        "info": "The Health Sector Development Program (the HSDP), consisting of a program grant for policy reforms and an accompanying project grant, will support the Government's 7th Health Sector Development Plan,\u2026", 
        "locationName": "Xaignabouli", 
        "sectors": [
          "Health"
        ], 
        "status": "Implementation", 
        "title": "HEALTH SECTOR DEVELOPMENT PROGRAM - PROJECT GRANT"
      }, 
      "type": "Feature"
    }, 
    {
      "geometry": {
        "coordinates": [
          102.41667, 
          18.75
        ], 
        "type": "Point"
      }, 
      "id": "7800", 
      "properties": {
        "approvalDate": "2009-11-23", 
        "closingDate": "2015-06-30", 
        "commitmentAmount": 10000000.0, 
        "disbursementAmount": 9999999.999999998, 
        "id": "41376-022", 
        "info": "The Health Sector Development Program (the HSDP), consisting of a program grant for policy reforms and an accompanying project grant, will support the Government's 7th Health Sector Development Plan,\u2026", 
        "locationName": "Vientiane Province", 
        "sectors": [
          "Health"
        ], 
        "status": "Implementation", 
        "title": "HEALTH SECTOR DEVELOPMENT PROGRAM - PROJECT GRANT"
      }, 
      "type": "Feature"
    }, 
    {
      "geometry": {
        "coordinates": [
          105.75, 
          16.5
        ], 
        "type": "Point"
      }, 
      "id": "7801", 
      "properties": {
        "approvalDate": "2009-11-23", 
        "closingDate": "2015-06-30", 
        "commitmentAmount": 10000000.0, 
        "disbursementAmount": 9999999.999999998, 
        "id": "41376-022", 
        "info": "The Health Sector Development Program (the HSDP), consisting of a program grant for policy reforms and an accompanying project grant, will support the Government's 7th Health Sector Development Plan,\u2026", 
        "locationName": "Khoueng Savannakhet", 
        "sectors": [
          "Health"
        ], 
        "status": "Implementation", 
        "title": "HEALTH SECTOR DEVELOPMENT PROGRAM - PROJECT GRANT"
      }, 
      "type": "Feature"
    }, 
    {
      "geometry": {
        "coordinates": [
          106.25, 
          15.75
        ], 
        "type": "Point"
      }, 
      "id": "7802", 
      "properties": {
        "approvalDate": "2009-11-23", 
        "closingDate": "2015-06-30", 
        "commitmentAmount": 10000000.0, 
        "disbursementAmount": 9999999.999999998, 
        "id": "41376-022", 
        "info": "The Health Sector Development Program (the HSDP), consisting of a program grant for policy reforms and an accompanying project grant, will support the Government's 7th Health Sector Development Plan,\u2026", 
        "locationName": "Salavan", 
        "sectors": [
          "Health"
        ], 
        "status": "Implementation", 
        "title": "HEALTH SECTOR DEVELOPMENT PROGRAM - PROJECT GRANT"
      }, 
      "type": "Feature"
    }, 
    {
      "geometry": {
        "coordinates": [
          102.33333, 
          21.75
        ], 
        "type": "Point"
      }, 
      "id": "7803", 
      "properties": {
        "approvalDate": "2009-11-23", 
        "closingDate": "2015-06-30", 
        "commitmentAmount": 10000000.0, 
        "disbursementAmount": 9999999.999999998, 
        "id": "41376-022", 
        "info": "The Health Sector Development Program (the HSDP), consisting of a program grant for policy reforms and an accompanying project grant, will support the Government's 7th Health Sector Development Plan,\u2026", 
        "locationName": "Khoueng Phongsali", 
        "sectors": [
          "Health"
        ], 
        "status": "Implementation", 
        "title": "HEALTH SECTOR DEVELOPMENT PROGRAM - PROJECT GRANT"
      }, 
      "type": "Feature"
    }, 
    {
      "geometry": {
        "coordinates": [
          101.5, 
          20.16667
        ], 
        "type": "Point"
      }, 
      "id": "7804", 
      "properties": {
        "approvalDate": "2009-11-23", 
        "closingDate": "2015-06-30", 
        "commitmentAmount": 10000000.0, 
        "disbursementAmount": 9999999.999999998, 
        "id": "41376-022", 
        "info": "The Health Sector Development Program (the HSDP), consisting of a program grant for policy reforms and an accompanying project grant, will support the Government's 7th Health Sector Development Plan,\u2026", 
        "locationName": "Khoueng Oudomxai", 
        "sectors": [
          "Health"
        ], 
        "status": "Implementation", 
        "title": "HEALTH SECTOR DEVELOPMENT PROGRAM - PROJECT GRANT"
      }, 
      "type": "Feature"
    }, 
    {
      "geometry": {
        "coordinates": [
          102.66667, 
          20.25
        ], 
        "type": "Point"
      }, 
      "id": "7805", 
      "properties": {
        "approvalDate": "2009-11-23", 
        "closingDate": "2015-06-30", 
        "commitmentAmount": 10000000.0, 
        "disbursementAmount": 9999999.999999998, 
        "id": "41376-022", 
        "info": "The Health Sector Development Program (the HSDP), consisting of a program grant for policy reforms and an accompanying project grant, will support the Government's 7th Health Sector Development Plan,\u2026", 
        "locationName": "Luang Prabang Province", 
        "sectors": [
          "Health"
        ], 
        "status": "Implementation", 
        "title": "HEALTH SECTOR DEVELOPMENT PROGRAM - PROJECT GRANT"
      }, 
      "type": "Feature"
    }, 
    {
      "geometry": {
        "coordinates": [
          101.33333, 
          20.91667
        ], 
        "type": "Point"
      }, 
      "id": "7806", 
      "properties": {
        "approvalDate": "2009-11-23", 
        "closingDate": "2015-06-30", 
        "commitmentAmount": 10000000.0, 
        "disbursementAmount": 9999999.999999998, 
        "id": "41376-022", 
        "info": "The Health Sector Development Program (the HSDP), consisting of a program grant for policy reforms and an accompanying project grant, will support the Government's 7th Health Sector Development Plan,\u2026", 
        "locationName": "Louangnamtha", 
        "sectors": [
          "Health"
        ], 
        "status": "Implementation", 
        "title": "HEALTH SECTOR DEVELOPMENT PROGRAM - PROJECT GRANT"
      }, 
      "type": "Feature"
    }, 
    {
      "geometry": {
        "coordinates": [
          105.33333, 
          17.5
        ], 
        "type": "Point"
      }, 
      "id": "7807", 
      "properties": {
        "approvalDate": "2009-11-23", 
        "closingDate": "2015-06-30", 
        "commitmentAmount": 10000000.0, 
        "disbursementAmount": 9999999.999999998, 
        "id": "41376-022", 
        "info": "The Health Sector Development Program (the HSDP), consisting of a program grant for policy reforms and an accompanying project grant, will support the Government's 7th Health Sector Development Plan,\u2026", 
        "locationName": "Khammouan", 
        "sectors": [
          "Health"
        ], 
        "status": "Implementation", 
        "title": "HEALTH SECTOR DEVELOPMENT PROGRAM - PROJECT GRANT"
      }, 
      "type": "Feature"
    }, 
    {
      "geometry": {
        "coordinates": [
          104.0, 
          20.5
        ], 
        "type": "Point"
      }, 
      "id": "7808", 
      "properties": {
        "approvalDate": "2009-11-23", 
        "closingDate": "2015-06-30", 
        "commitmentAmount": 10000000.0, 
        "disbursementAmount": 9999999.999999998, 
        "id": "41376-022", 
        "info": "The Health Sector Development Program (the HSDP), consisting of a program grant for policy reforms and an accompanying project grant, will support the Government's 7th Health Sector Development Plan,\u2026", 
        "locationName": "Houaphan", 
        "sectors": [
          "Health"
        ], 
        "status": "Implementation", 
        "title": "HEALTH SECTOR DEVELOPMENT PROGRAM - PROJECT GRANT"
      }, 
      "type": "Feature"
    }, 
    {
      "geometry": {
        "coordinates": [
          106.0, 
          14.75
        ], 
        "type": "Point"
      }, 
      "id": "7809", 
      "properties": {
        "approvalDate": "2009-11-23", 
        "closingDate": "2015-06-30", 
        "commitmentAmount": 10000000.0, 
        "disbursementAmount": 9999999.999999998, 
        "id": "41376-022", 
        "info": "The Health Sector Development Program (the HSDP), consisting of a program grant for policy reforms and an accompanying project grant, will support the Government's 7th Health Sector Development Plan,\u2026", 
        "locationName": "Champasak", 
        "sectors": [
          "Health"
        ], 
        "status": "Implementation", 
        "title": "HEALTH SECTOR DEVELOPMENT PROGRAM - PROJECT GRANT"
      }, 
      "type": "Feature"
    }, 
    {
      "geometry": {
        "coordinates": [
          102.6, 
          17.96667
        ], 
        "type": "Point"
      }, 
      "id": "7810", 
      "properties": {
        "approvalDate": "2009-11-23", 
        "closingDate": "2015-06-30", 
        "commitmentAmount": 10000000.0, 
        "disbursementAmount": 9999999.999999998, 
        "id": "41376-022", 
        "info": "The Health Sector Development Program (the HSDP), consisting of a program grant for policy reforms and an accompanying project grant, will support the Government's 7th Health Sector Development Plan,\u2026", 
        "locationName": "Vientiane", 
        "sectors": [
          "Health"
        ], 
        "status": "Implementation", 
        "title": "HEALTH SECTOR DEVELOPMENT PROGRAM - PROJECT GRANT"
      }, 
      "type": "Feature"
    }, 
    {
      "geometry": {
        "coordinates": [
          103.5, 
          19.41667
        ], 
        "type": "Point"
      }, 
      "id": "7811", 
      "properties": {
        "approvalDate": "2009-11-23", 
        "closingDate": "2015-06-30", 
        "commitmentAmount": 10000000.0, 
        "disbursementAmount": 9999999.999999998, 
        "id": "41376-022", 
        "info": "The Health Sector Development Program (the HSDP), consisting of a program grant for policy reforms and an accompanying project grant, will support the Government's 7th Health Sector Development Plan,\u2026", 
        "locationName": "Xiangkhouang", 
        "sectors": [
          "Health"
        ], 
        "status": "Implementation", 
        "title": "HEALTH SECTOR DEVELOPMENT PROGRAM - PROJECT GRANT"
      }, 
      "type": "Feature"
    }, 
    {
      "geometry": {
        "coordinates": [
          107.0, 
          14.66667
        ], 
        "type": "Point"
      }, 
      "id": "7812", 
      "properties": {
        "approvalDate": "2009-11-23", 
        "closingDate": "2015-06-30", 
        "commitmentAmount": 10000000.0, 
        "disbursementAmount": 9999999.999999998, 
        "id": "41376-022", 
        "info": "The Health Sector Development Program (the HSDP), consisting of a program grant for policy reforms and an accompanying project grant, will support the Government's 7th Health Sector Development Plan,\u2026", 
        "locationName": "Attapu", 
        "sectors": [
          "Health"
        ], 
        "status": "Implementation", 
        "title": "HEALTH SECTOR DEVELOPMENT PROGRAM - PROJECT GRANT"
      }, 
      "type": "Feature"
    }, 
    {
      "geometry": {
        "coordinates": [
          107.0, 
          15.5
        ], 
        "type": "Point"
      }, 
      "id": "7813", 
      "properties": {
        "approvalDate": "2009-11-23", 
        "closingDate": "2015-06-30", 
        "commitmentAmount": 10000000.0, 
        "disbursementAmount": 9999999.999999998, 
        "id": "41376-022", 
        "info": "The Health Sector Development Program (the HSDP), consisting of a program grant for policy reforms and an accompanying project grant, will support the Government's 7th Health Sector Development Plan,\u2026", 
        "locationName": "Khoueng Xekong", 
        "sectors": [
          "Health"
        ], 
        "status": "Implementation", 
        "title": "HEALTH SECTOR DEVELOPMENT PROGRAM - PROJECT GRANT"
      }, 
      "type": "Feature"
    }, 
    {
      "geometry": {
        "coordinates": [
          100.5, 
          20.5
        ], 
        "type": "Point"
      }, 
      "id": "7814", 
      "properties": {
        "approvalDate": "2009-11-23", 
        "closingDate": "2015-06-30", 
        "commitmentAmount": 10000000.0, 
        "disbursementAmount": 9999999.999999998, 
        "id": "41376-022", 
        "info": "The Health Sector Development Program (the HSDP), consisting of a program grant for policy reforms and an accompanying project grant, will support the Government's 7th Health Sector Development Plan,\u2026", 
        "locationName": "Khoueng Bokeo", 
        "sectors": [
          "Health"
        ], 
        "status": "Implementation", 
        "title": "HEALTH SECTOR DEVELOPMENT PROGRAM - PROJECT GRANT"
      }, 
      "type": "Feature"
    }, 
    {
      "geometry": {
        "coordinates": [
          104.33333, 
          18.5
        ], 
        "type": "Point"
      }, 
      "id": "7815", 
      "properties": {
        "approvalDate": "2009-11-23", 
        "closingDate": "2015-06-30", 
        "commitmentAmount": 10000000.0, 
        "disbursementAmount": 9999999.999999998, 
        "id": "41376-022", 
        "info": "The Health Sector Development Program (the HSDP), consisting of a program grant for policy reforms and an accompanying project grant, will support the Government's 7th Health Sector Development Plan,\u2026", 
        "locationName": "Bolikhamxai", 
        "sectors": [
          "Health"
        ], 
        "status": "Implementation", 
        "title": "HEALTH SECTOR DEVELOPMENT PROGRAM - PROJECT GRANT"
      }, 
      "type": "Feature"
    }, 
    {
      "geometry": {
        "coordinates": [
          102.66667, 
          18.08333
        ], 
        "type": "Point"
      }, 
      "id": "7816", 
      "properties": {
        "approvalDate": "2009-11-23", 
        "closingDate": "2015-06-30", 
        "commitmentAmount": 10000000.0, 
        "disbursementAmount": 9999999.999999998, 
        "id": "41376-022", 
        "info": "The Health Sector Development Program (the HSDP), consisting of a program grant for policy reforms and an accompanying project grant, will support the Government's 7th Health Sector Development Plan,\u2026", 
        "locationName": "Vientiane Prefecture", 
        "sectors": [
          "Health"
        ], 
        "status": "Implementation", 
        "title": "HEALTH SECTOR DEVELOPMENT PROGRAM - PROJECT GRANT"
      }, 
      "type": "Feature"
    }
  ], 
  "id": "LA", 
  "properties": {
    "bounds": [
      100.0970732020001, 
      13.91545664500012, 
      107.66436324000011, 
      22.49604400700011
    ], 
    "metadata": {
      "data_origin": "http://www.adb.org/iati/iati-activities-la.xml", 
      "download_date": "2015-07-06 18:12:35", 
      "quarter": "Q3 2015", 
      "run_date": "2015-07-06 18:12:49"
    }, 
    "name": "Lao PDR"
  }, 
  "type": "FeatureCollection"
}