{"info": "A policy-based loan of $200 million for the Punjab Development Finance Program that seeks to facilitate implementation of a comprehensive fiscal consolidation program in Punjab. This will generate fiscal savings and thereby assist Punjab to augment and sustain growth enhancing development financing.", "bounds": [[68.1434025400001, 6.74555084800015, 97.36225305200006, 35.49540557900009]], "locations": {"geometry": {"type": "MultiPoint", "coordinates": []}, "type": "Feature"}, "name": "PUNJAB DEVELOPMENT FINANCE PROGRAM", "id": "46004-45288-002-LN3187"}